{
  "hash": "e2d1f9fb",
  "configHash": "7c3cfa9e",
  "lockfileHash": "963e6ef1",
  "browserHash": "32eb9522",
  "optimized": {
    "@angular/core": {
      "src": "../../../../../node_modules/@angular/core/fesm2022/core.mjs",
      "file": "@angular_core.js",
      "fileHash": "523d7d50",
      "needsInterop": false
    },
    "@angular/platform-browser": {
      "src": "../../../../../node_modules/@angular/platform-browser/fesm2022/platform-browser.mjs",
      "file": "@angular_platform-browser.js",
      "fileHash": "d0bfc6b9",
      "needsInterop": false
    },
    "@angular/router": {
      "src": "../../../../../node_modules/@angular/router/fesm2022/router.mjs",
      "file": "@angular_router.js",
      "fileHash": "916efd00",
      "needsInterop": false
    }
  },
  "chunks": {
    "chunk-35AOMQM3": {
      "file": "chunk-35AOMQM3.js"
    },
    "chunk-GSEU53OH": {
      "file": "chunk-GSEU53OH.js"
    }
  }
}